{
  "owner_id": "22auvhdoqxfrv4t7stdgfxqha",
  "id": "4clxjD9QarucZ77zTApdhR",
  "name": "Drum&Basssssss",
  "tracks": [
    {
      "added_at": "2021-06-05T22:21:36Z",
      "added_by_id": "22auvhdoqxfrv4t7stdgfxqha",
      "id": "7wjAu7AeBQFDVhSXQQ4Ji5",
      "name": "The Change (feat. DMA’S)",
      "artists": [
        {
          "id": "4AA8eXtzqh5ykxtafLaPOi",
          "name": "What So Not",
          "type": "artist"
        },
        {
          "id": "1iUTUix5kea176M0uJTsh4",
          "name": "DMA'S",
          "type": "artist"
        }
      ],
      "duration": 277555,
      "track_number": 1,
      "type": "track",
      "is_local": false
    },
    {
      "added_at": "2021-06-05T22:23:12Z",
      "added_by_id": "22auvhdoqxfrv4t7stdgfxqha",
      "id": "6cq5CiTm239TeNEE6YjqfE",
      "name": "Butterflies",
      "artists": [
        {
          "id": "5he5w2lnU9x7JFhnwcekXX",
          "name": "Skrillex",
          "type": "artist"
        },
        {
          "id": "6DpWtzfwV8fcwP6fXckDVu",
          "name": "Starrah",
          "type": "artist"
        },
        {
          "id": "7Eu1txygG6nJttLHbZdQOh",
          "name": "Four Tet",
          "type": "artist"
        }
      ],
      "duration": 195937,
      "track_number": 1,
      "type": "track",
      "is_local": false
    },
    {
      "added_at": "2021-06-05T22:23:51Z",
      "added_by_id": "22auvhdoqxfrv4t7stdgfxqha",
      "id": "4nlvKIIetOWGIMyhjQXgOZ",
      "name": "The Difference",
      "artists": [
        {
          "id": "6nxWCVXbOlEVRexSbLsTer",
          "name": "Flume",
          "type": "artist"
        },
        {
          "id": "6O4EGCCb6DoIiR6B1QCQgp",
          "name": "Toro y Moi",
          "type": "artist"
        }
      ],
      "duration": 139662,
      "track_number": 1,
      "type": "track",
      "is_local": false
    },
    {
      "added_at": "2021-06-05T22:35:26Z",
      "added_by_id": "22auvhdoqxfrv4t7stdgfxqha",
      "id": "5Dv6S0ds5gRUlmUV0kONEL",
      "name": "Treat You Right",
      "artists": [
        {
          "id": "6wFwvxJkurQPU2UdeD4qVt",
          "name": "The Jungle Giants",
          "type": "artist"
        }
      ],
      "duration": 221466,
      "track_number": 1,
      "type": "track",
      "is_local": false
    },
    {
      "added_at": "2021-11-13T18:00:37Z",
      "added_by_id": "22auvhdoqxfrv4t7stdgfxqha",
      "id": "4HRVvrMFXvtSnw3J3knPV1",
      "name": "Reflections",
      "artists": [
        {
          "id": "2n7USVO8fO8FF8zq4kG2N1",
          "name": "Mat Zo",
          "type": "artist"
        },
        {
          "id": "1gMMbPTZtOb9W3IBYl6twO",
          "name": "OLAN",
          "type": "artist"
        }
      ],
      "duration": 267907,
      "track_number": 1,
      "type": "track",
      "is_local": false
    },
    {
      "added_at": "2021-11-13T18:10:36Z",
      "added_by_id": "22auvhdoqxfrv4t7stdgfxqha",
      "id": "0VPtIe8j9wZMVTcYWURQGd",
      "name": "Sientelo",
      "artists": [
        {
          "id": "54qqaSH6byJIb8eFWxe3Pj",
          "name": "Mefjus",
          "type": "artist"
        },
        {
          "id": "2N8IPNZTiNo3nj4mreOlHU",
          "name": "Camo & Krooked",
          "type": "artist"
        }
      ],
      "duration": 290742,
      "track_number": 1,
      "type": "track",
      "is_local": false
    },
    {
      "added_at": "2021-11-24T06:41:20Z",
      "added_by_id": "22auvhdoqxfrv4t7stdgfxqha",
      "id": "4QayV7ZAp4f7A8XIIUH0oD",
      "name": "Vibin'",
      "artists": [
        {
          "id": "2w5c2l70mYNDdSLifFyZjJ",
          "name": "Monty",
          "type": "artist"
        },
        {
          "id": "1QEJm4mWKmrboH7if0CYoL",
          "name": "Visages",
          "type": "artist"
        }
      ],
      "duration": 286896,
      "track_number": 1,
      "type": "track",
      "is_local": false
    },
    {
      "added_at": "2023-01-06T16:43:43Z",
      "added_by_id": "22auvhdoqxfrv4t7stdgfxqha",
      "id": "2mobDDzkskezluhIzhM7Sg",
      "name": "Way Back",
      "artists": [
        {
          "id": "5he5w2lnU9x7JFhnwcekXX",
          "name": "Skrillex",
          "type": "artist"
        },
        {
          "id": "78rUTD7y6Cy67W1RVzYs7t",
          "name": "PinkPantheress",
          "type": "artist"
        },
        {
          "id": "6Xgp2XMz1fhVYe7i6yNAax",
          "name": "Trippie Redd",
          "type": "artist"
        }
      ],
      "duration": 119314,
      "track_number": 1,
      "type": "track",
      "is_local": false
    },
    {
      "added_at": "2023-01-21T06:22:13Z",
      "added_by_id": "22auvhdoqxfrv4t7stdgfxqha",
      "id": "7vzWtCVhEKDmDkMmT3AiUL",
      "name": "Leave Me Like This",
      "artists": [
        {
          "id": "5he5w2lnU9x7JFhnwcekXX",
          "name": "Skrillex",
          "type": "artist"
        },
        {
          "id": "22g86cix6LCeLMbu3m91Wo",
          "name": "Bobby Raps",
          "type": "artist"
        }
      ],
      "duration": 188571,
      "track_number": 1,
      "type": "track",
      "is_local": false
    },
    {
      "added_at": "2023-04-28T12:44:49Z",
      "added_by_id": "22auvhdoqxfrv4t7stdgfxqha",
      "id": "4CbUeLEp5QJJYSYm59Cozy",
      "name": "Always in a Hurry",
      "artists": [
        {
          "id": "62vbsDRAq0qHdezaCOzB0T",
          "name": "Medasin",
          "type": "artist"
        }
      ],
      "duration": 164769,
      "track_number": 1,
      "type": "track",
      "is_local": false
    }
  ]
}